src/convertidorsynt.v
/* Generated by Yosys 0.7 (git sha1 61f6811, gcc 6.2.0-10 -O2 -fdebug-prefix-map=/build/yosys-0DEyT5/yosys-0.7=. -fstack-protector-strong -fPIC -Os) */
`include "cmos_cells.v"
module convertidorsynt(PCLK, in, out_8, ENB, CLK, bits);
  wire [7:0] _000_;
  wire [1:0] _001_;
  wire _002_;
  wire _003_;
  wire _004_;
  wire _005_;
  wire _006_;
  wire _007_;
  wire _008_;
  wire _009_;
  wire _010_;
  wire _011_;
  wire _012_;
  wire _013_;
  wire _014_;
  wire _015_;
  wire _016_;
  wire _017_;
  wire _018_;
  wire _019_;
  wire _020_;
  wire _021_;
  wire _022_;
  wire _023_;
  wire _024_;
  wire _025_;
  wire _026_;
  wire _027_;
  wire _028_;
  wire _029_;
  wire _030_;
  wire _031_;
  wire _032_;
  wire _033_;
  wire _034_;
  wire _035_;
  wire _036_;
  wire _037_;
  wire _038_;
  wire _039_;
  wire _040_;
  wire _041_;
  wire _042_;
  wire _043_;
  wire _044_;
  wire _045_;
  wire _046_;
  wire _047_;
  wire _048_;
  wire _049_;
  wire _050_;
  wire _051_;
  wire _052_;
  wire _053_;
  wire _054_;
  wire _055_;
  wire _056_;
  wire _057_;
  wire _058_;
  wire _059_;
  wire _060_;
  wire _061_;
  wire _062_;
  wire _063_;
  wire _064_;
  wire _065_;
  wire _066_;
  wire _067_;
  wire _068_;
  wire _069_;
  wire _070_;
  wire _071_;
  wire _072_;
  wire _073_;
  wire _074_;
  wire _075_;
  wire _076_;
  wire _077_;
  wire _078_;
  wire _079_;
  wire _080_;
  wire _081_;
  wire _082_;
  wire _083_;
  wire _084_;
  wire _085_;
  wire _086_;
  wire _087_;
  wire _088_;
  wire _089_;
  wire _090_;
  wire _091_;
  wire _092_;
  wire _093_;
  wire _094_;
  wire _095_;
  wire _096_;
  wire _097_;
  wire _098_;
  wire _099_;
  wire _100_;
  wire _101_;
  wire _102_;
  wire _103_;
  wire _104_;
  wire _105_;
  wire _106_;
  wire [1:0] _107_;
  wire [1:0] _108_;
  wire [1:0] _109_;
  wire _110_;
  wire _111_;
  wire _112_;
  wire _113_;
  wire _114_;
  wire _115_;
  wire [7:0] _116_;
  wire [7:0] _117_;
  wire [1:0] _118_;
  wire [1:0] _119_;
  wire [1:0] _120_;
  wire [5:0] _121_;
  wire [1:0] _122_;
  wire _123_;
  wire _124_;
  wire _125_;
  wire [7:0] _126_;
  wire _127_;
  input CLK;
  input ENB;
  input [1:0] PCLK;
  output [1:0] bits;
  input [31:0] in;
  output [7:0] out_8;
  NOT _128_ (
    .A(_075_),
    .Y(_032_)
  );
  NAND _129_ (
    .A(_032_),
    .B(_047_),
    .Y(_033_)
  );
  NOT _130_ (
    .A(_047_),
    .Y(_035_)
  );
  NAND _131_ (
    .A(_075_),
    .B(_035_),
    .Y(_091_)
  );
  NAND _132_ (
    .A(_091_),
    .B(_033_),
    .Y(_037_)
  );
  NOT _133_ (
    .A(_037_),
    .Y(_002_)
  );
  NOT _134_ (
    .A(_073_),
    .Y(_039_)
  );
  NOT _135_ (
    .A(_051_),
    .Y(_040_)
  );
  NOR _136_ (
    .A(_037_),
    .B(_040_),
    .Y(_042_)
  );
  NOR _137_ (
    .A(_075_),
    .B(_035_),
    .Y(_043_)
  );
  NAND _138_ (
    .A(_043_),
    .B(_014_),
    .Y(_045_)
  );
  NOR _139_ (
    .A(_032_),
    .B(_047_),
    .Y(_046_)
  );
  NAND _140_ (
    .A(_046_),
    .B(_015_),
    .Y(_049_)
  );
  NAND _141_ (
    .A(_049_),
    .B(_045_),
    .Y(_050_)
  );
  NOR _142_ (
    .A(_050_),
    .B(_042_),
    .Y(_052_)
  );
  NOR _143_ (
    .A(_052_),
    .B(_039_),
    .Y(_076_)
  );
  NOT _144_ (
    .A(_053_),
    .Y(_054_)
  );
  NOR _145_ (
    .A(_037_),
    .B(_054_),
    .Y(_055_)
  );
  NAND _146_ (
    .A(_043_),
    .B(_016_),
    .Y(_057_)
  );
  NAND _147_ (
    .A(_046_),
    .B(_017_),
    .Y(_058_)
  );
  NAND _148_ (
    .A(_058_),
    .B(_057_),
    .Y(_060_)
  );
  NOR _149_ (
    .A(_060_),
    .B(_055_),
    .Y(_061_)
  );
  NOR _150_ (
    .A(_061_),
    .B(_039_),
    .Y(_078_)
  );
  NOT _151_ (
    .A(_056_),
    .Y(_063_)
  );
  NOR _152_ (
    .A(_037_),
    .B(_063_),
    .Y(_065_)
  );
  NAND _153_ (
    .A(_043_),
    .B(_018_),
    .Y(_066_)
  );
  NAND _154_ (
    .A(_046_),
    .B(_019_),
    .Y(_068_)
  );
  NAND _155_ (
    .A(_068_),
    .B(_066_),
    .Y(_069_)
  );
  NOR _156_ (
    .A(_069_),
    .B(_065_),
    .Y(_071_)
  );
  NOR _157_ (
    .A(_071_),
    .B(_039_),
    .Y(_080_)
  );
  NOT _158_ (
    .A(_059_),
    .Y(_072_)
  );
  NOR _159_ (
    .A(_037_),
    .B(_072_),
    .Y(_074_)
  );
  NAND _160_ (
    .A(_043_),
    .B(_020_),
    .Y(_077_)
  );
  NAND _161_ (
    .A(_046_),
    .B(_021_),
    .Y(_079_)
  );
  NAND _162_ (
    .A(_079_),
    .B(_077_),
    .Y(_081_)
  );
  NOR _163_ (
    .A(_081_),
    .B(_074_),
    .Y(_083_)
  );
  NOR _164_ (
    .A(_083_),
    .B(_039_),
    .Y(_082_)
  );
  NOT _165_ (
    .A(_062_),
    .Y(_086_)
  );
  NOR _166_ (
    .A(_037_),
    .B(_086_),
    .Y(_088_)
  );
  NAND _167_ (
    .A(_043_),
    .B(_022_),
    .Y(_090_)
  );
  NAND _168_ (
    .A(_046_),
    .B(_023_),
    .Y(_092_)
  );
  NAND _169_ (
    .A(_092_),
    .B(_090_),
    .Y(_093_)
  );
  NOR _170_ (
    .A(_093_),
    .B(_088_),
    .Y(_094_)
  );
  NOR _171_ (
    .A(_094_),
    .B(_039_),
    .Y(_084_)
  );
  NOT _172_ (
    .A(_064_),
    .Y(_095_)
  );
  NOR _173_ (
    .A(_037_),
    .B(_095_),
    .Y(_096_)
  );
  NAND _174_ (
    .A(_043_),
    .B(_024_),
    .Y(_097_)
  );
  NAND _175_ (
    .A(_046_),
    .B(_025_),
    .Y(_098_)
  );
  NAND _176_ (
    .A(_098_),
    .B(_097_),
    .Y(_100_)
  );
  NOR _177_ (
    .A(_100_),
    .B(_096_),
    .Y(_102_)
  );
  NOR _178_ (
    .A(_102_),
    .B(_039_),
    .Y(_085_)
  );
  NOT _179_ (
    .A(_067_),
    .Y(_103_)
  );
  NOR _180_ (
    .A(_037_),
    .B(_103_),
    .Y(_003_)
  );
  NAND _181_ (
    .A(_043_),
    .B(_026_),
    .Y(_004_)
  );
  NAND _182_ (
    .A(_046_),
    .B(_027_),
    .Y(_005_)
  );
  NAND _183_ (
    .A(_005_),
    .B(_004_),
    .Y(_006_)
  );
  NOR _184_ (
    .A(_006_),
    .B(_003_),
    .Y(_007_)
  );
  NOR _185_ (
    .A(_007_),
    .B(_039_),
    .Y(_087_)
  );
  NOT _186_ (
    .A(_070_),
    .Y(_008_)
  );
  NOR _187_ (
    .A(_037_),
    .B(_008_),
    .Y(_009_)
  );
  NAND _188_ (
    .A(_043_),
    .B(_028_),
    .Y(_010_)
  );
  NAND _189_ (
    .A(_046_),
    .B(_029_),
    .Y(_011_)
  );
  NAND _190_ (
    .A(_011_),
    .B(_010_),
    .Y(_012_)
  );
  NOR _191_ (
    .A(_012_),
    .B(_009_),
    .Y(_013_)
  );
  NOR _192_ (
    .A(_013_),
    .B(_039_),
    .Y(_089_)
  );
  NOR _193_ (
    .A(_046_),
    .B(_073_),
    .Y(_099_)
  );
  NOT _194_ (
    .A(_037_),
    .Y(_101_)
  );
  DFF _195_ (
    .C(CLK),
    .D(_000_[0]),
    .Q(out_8[0])
  );
  DFF _196_ (
    .C(CLK),
    .D(_000_[1]),
    .Q(out_8[1])
  );
  DFF _197_ (
    .C(CLK),
    .D(_000_[2]),
    .Q(out_8[2])
  );
  DFF _198_ (
    .C(CLK),
    .D(_000_[3]),
    .Q(out_8[3])
  );
  DFF _199_ (
    .C(CLK),
    .D(_000_[4]),
    .Q(out_8[4])
  );
  DFF _200_ (
    .C(CLK),
    .D(_000_[5]),
    .Q(out_8[5])
  );
  DFF _201_ (
    .C(CLK),
    .D(_000_[6]),
    .Q(out_8[6])
  );
  DFF _202_ (
    .C(CLK),
    .D(_000_[7]),
    .Q(out_8[7])
  );
  DFF _203_ (
    .C(CLK),
    .D(_001_[0]),
    .Q(bits[0])
  );
  DFF _204_ (
    .C(CLK),
    .D(_001_[1]),
    .Q(bits[1])
  );
  assign bits[1] = _002_;
  assign _047_ = PCLK[0];
  assign _075_ = PCLK[1];
  assign _014_ = in[8];
  assign _015_ = in[0];
  assign _016_ = in[9];
  assign _017_ = in[1];
  assign _018_ = in[10];
  assign _019_ = in[2];
  assign _020_ = in[11];
  assign _021_ = in[3];
  assign _022_ = in[12];
  assign _023_ = in[4];
  assign _024_ = in[13];
  assign _025_ = in[5];
  assign _026_ = in[14];
  assign _027_ = in[6];
  assign _028_ = in[15];
  assign _029_ = in[7];
  assign _030_ = in[16];
  assign _031_ = in[17];
  assign _034_ = in[18];
  assign _036_ = in[19];
  assign _038_ = in[20];
  assign _041_ = in[21];
  assign _044_ = in[22];
  assign _048_ = in[23];
  assign _051_ = in[24];
  assign _053_ = in[25];
  assign _056_ = in[26];
  assign _059_ = in[27];
  assign _062_ = in[28];
  assign _064_ = in[29];
  assign _067_ = in[30];
  assign _070_ = in[31];
  assign _073_ = ENB;
  assign _000_[0] = _076_;
  assign _000_[1] = _078_;
  assign _000_[2] = _080_;
  assign _000_[3] = _082_;
  assign _000_[4] = _084_;
  assign _000_[5] = _085_;
  assign _000_[6] = _087_;
  assign _000_[7] = _089_;
  assign bits[0] = _091_;
  assign _001_[0] = _099_;
  assign _001_[1] = _101_;
endmodule

src/convertidor.v
module convertidor(PCLK,in,out_8,ENB,CLK,bits);
		input wire [1:0] PCLK;
		input wire CLK;
		input wire ENB;
		input wire [31:0] in;
		output reg [7:0] out_8;
		output reg [1:0] bits;
		always @(*)
		begin
		case(PCLK[1:0])
			2'b00: bits=2'b11;
			2'b01: bits=2'b01;
			2'b10: bits=2'b00;
			2'b11: bits=2'b11;
		endcase
		end
		always @(posedge CLK) begin
			if(ENB==1) begin
				if(bits==2'b11)begin
					out_8[7:0]<=in[31:24];
					bits<=2'b10;
				end 
				else if(bits==2'b10)begin
					out_8[7:0]<=in[23:16];
					bits<=2'b01;
				end 
				else if(bits==2'b01)begin
					out_8[7:0]<=in[15:8];
					bits<=2'b00;
				end
				else //(bits==2'b00)
				begin
					out_8[7:0]<=in[7:0];
				end 
			end
			else 
			begin
				out_8=0;
			end	
		end
	endmodule

src/probador_conv.v
module probador_conv(PCLK,ENB,in,CLK);

	output reg [1:0] PCLK;
	output reg CLK;
	output reg ENB;
  	output reg [31:0] in;
	
	initial begin
		CLK=0;
		ENB=0;
		
		#20 ENB=1;
		#80
		PCLK<=2'b00;//32bits
        	in<=32'b00001111000000001111111101010101;
		#75
		PCLK<=2'b01;//16bits
		
		#5
        	in<=32'b0011000011101010;
		
		#80
		PCLK<=2'b10;//8bits
        	in<=32'b10101110;
	
		#150
	  	$finish;
	end
	always begin
        	#10 CLK <= ~CLK;
      	end
	
endmodule

src/probador_conv_tb.v
`include "convertidor.v"
`include "convertidorsynt.v"
`include "probador_conv.v"

module probador_conv_tb();

input wire [1:0] PCLK;
input wire [31:0] in_data;
input wire CLK, ENB;
output wire [7:0] OUT_DATA;
output wire [1:0] bit;

probador_conv p(PCLK,ENB,in_data,CLK);
convertidor conv(PCLK, in_data, OUT_DATA, ENB, CLK, bit);
convertidorsynt convsynt(PCLK,in_data, OUT_DATA, ENB, CLK, bit);


initial 
	begin
	$dumpfile("conv328.vcd");
	$dumpvars;
	end

endmodule

src/cmos_cellspotencia.v

module BUF(A, Y);
	input A;
	output Y;
	assign Y = A;
endmodule

module NOT(A, Y);
	input A;
	output Y;
	assign Y = ~A;
endmodule

module NAND(A, B, Y);
	input A, B;
	output Y;
	assign Y = ~(A & B);
endmodule

module NOR(A, B, Y);
	input A, B;
	output Y;
	assign Y = ~(A | B);
endmodule

module DFF(C, D, Q);
	parameter
		PwrC = 0;
	input C, D;
	output reg Q;
	always @(posedge C) begin
		Q <= D;
	end
	always @(posedge Q) begin
		tb_tx.m1.PwrCntr[PwrC] = tb_tx.m1.PwrCntr[PwrC] + 1;
	end
endmodule

module DFFSR(C, D, Q, S, R);
	input C, D, S, R;
	output reg Q;
	always @(posedge C, posedge S, posedge R)
		if (S)
			Q <= 1'b1;
		else if (R)
			Q <= 1'b0;
		else
			Q <= D;
endmodule

src/conv328.vcd
$date
	Mon Oct 16 20:25:15 2017
$end
$version
	Icarus Verilog
$end
$timescale
	1s
$end
$scope module BUF $end
$var wire 1 ! A $end
$var wire 1 " Y $end
$upscope $end
$scope module DFFSR $end
$var wire 1 # C $end
$var wire 1 $ D $end
$var wire 1 % R $end
$var wire 1 & S $end
$var reg 1 ' Q $end
$upscope $end
$scope module probador_conv_tb $end
$var wire 8 ( OUT_DATA [7:0] $end
$var wire 2 ) bit [1:0] $end
$var wire 32 * in_data [31:0] $end
$var wire 2 + PCLK [1:0] $end
$var wire 1 , ENB $end
$var wire 1 - CLK $end
$scope module conv $end
$var wire 32 . in [31:0] $end
$var wire 2 / PCLK [1:0] $end
$var wire 1 , ENB $end
$var wire 1 - CLK $end
$var reg 2 0 bits [1:0] $end
$var reg 8 1 out_8 [7:0] $end
$upscope $end
$scope module convsynt $end
$var wire 1 2 _073_ $end
$var wire 2 3 bits [1:0] $end
$var wire 8 4 out_8 [7:0] $end
$var wire 32 5 in [31:0] $end
$var wire 1 6 _103_ $end
$var wire 1 7 _102_ $end
$var wire 1 8 _101_ $end
$var wire 1 9 _100_ $end
$var wire 1 : _099_ $end
$var wire 1 ; _098_ $end
$var wire 1 < _097_ $end
$var wire 1 = _096_ $end
$var wire 1 > _095_ $end
$var wire 1 ? _094_ $end
$var wire 1 @ _093_ $end
$var wire 1 A _092_ $end
$var wire 1 B _091_ $end
$var wire 1 C _090_ $end
$var wire 1 D _089_ $end
$var wire 1 E _088_ $end
$var wire 1 F _087_ $end
$var wire 1 G _086_ $end
$var wire 1 H _085_ $end
$var wire 1 I _084_ $end
$var wire 1 J _083_ $end
$var wire 1 K _082_ $end
$var wire 1 L _081_ $end
$var wire 1 M _080_ $end
$var wire 1 N _079_ $end
$var wire 1 O _078_ $end
$var wire 1 P _077_ $end
$var wire 1 Q _076_ $end
$var wire 1 R _075_ $end
$var wire 1 S _074_ $end
$var wire 1 T _072_ $end
$var wire 1 U _071_ $end
$var wire 1 V _070_ $end
$var wire 1 W _069_ $end
$var wire 1 X _068_ $end
$var wire 1 Y _067_ $end
$var wire 1 Z _066_ $end
$var wire 1 [ _065_ $end
$var wire 1 \ _064_ $end
$var wire 1 ] _063_ $end
$var wire 1 ^ _062_ $end
$var wire 1 _ _061_ $end
$var wire 1 ` _060_ $end
$var wire 1 a _059_ $end
$var wire 1 b _058_ $end
$var wire 1 c _057_ $end
$var wire 1 d _056_ $end
$var wire 1 e _055_ $end
$var wire 1 f _054_ $end
$var wire 1 g _053_ $end
$var wire 1 h _052_ $end
$var wire 1 i _051_ $end
$var wire 1 j _050_ $end
$var wire 1 k _049_ $end
$var wire 1 l _048_ $end
$var wire 1 m _047_ $end
$var wire 1 n _046_ $end
$var wire 1 o _045_ $end
$var wire 1 p _044_ $end
$var wire 1 q _043_ $end
$var wire 1 r _042_ $end
$var wire 1 s _041_ $end
$var wire 1 t _040_ $end
$var wire 1 u _039_ $end
$var wire 1 v _038_ $end
$var wire 1 w _037_ $end
$var wire 1 x _036_ $end
$var wire 1 y _035_ $end
$var wire 1 z _034_ $end
$var wire 1 { _033_ $end
$var wire 1 | _032_ $end
$var wire 1 } _031_ $end
$var wire 1 ~ _030_ $end
$var wire 1 !" _029_ $end
$var wire 1 "" _028_ $end
$var wire 1 #" _027_ $end
$var wire 1 $" _026_ $end
$var wire 1 %" _025_ $end
$var wire 1 &" _024_ $end
$var wire 1 '" _023_ $end
$var wire 1 (" _022_ $end
$var wire 1 )" _021_ $end
$var wire 1 *" _020_ $end
$var wire 1 +" _019_ $end
$var wire 1 ," _018_ $end
$var wire 1 -" _017_ $end
$var wire 1 ." _016_ $end
$var wire 1 /" _015_ $end
$var wire 1 0" _014_ $end
$var wire 1 1" _013_ $end
$var wire 1 2" _012_ $end
$var wire 1 3" _011_ $end
$var wire 1 4" _010_ $end
$var wire 1 5" _009_ $end
$var wire 1 6" _008_ $end
$var wire 1 7" _007_ $end
$var wire 1 8" _006_ $end
$var wire 1 9" _005_ $end
$var wire 1 :" _004_ $end
$var wire 1 ;" _003_ $end
$var wire 1 <" _002_ $end
$var wire 2 =" _001_ [1:0] $end
$var wire 8 >" _000_ [7:0] $end
$var wire 2 ?" PCLK [1:0] $end
$var wire 1 , ENB $end
$var wire 1 - CLK $end
$scope module _128_ $end
$var wire 1 R A $end
$var wire 1 | Y $end
$upscope $end
$scope module _129_ $end
$var wire 1 | A $end
$var wire 1 m B $end
$var wire 1 { Y $end
$upscope $end
$scope module _130_ $end
$var wire 1 m A $end
$var wire 1 y Y $end
$upscope $end
$scope module _131_ $end
$var wire 1 R A $end
$var wire 1 y B $end
$var wire 1 B Y $end
$upscope $end
$scope module _132_ $end
$var wire 1 B A $end
$var wire 1 { B $end
$var wire 1 w Y $end
$upscope $end
$scope module _133_ $end
$var wire 1 w A $end
$var wire 1 <" Y $end
$upscope $end
$scope module _134_ $end
$var wire 1 2 A $end
$var wire 1 u Y $end
$upscope $end
$scope module _135_ $end
$var wire 1 i A $end
$var wire 1 t Y $end
$upscope $end
$scope module _136_ $end
$var wire 1 w A $end
$var wire 1 t B $end
$var wire 1 r Y $end
$upscope $end
$scope module _137_ $end
$var wire 1 R A $end
$var wire 1 y B $end
$var wire 1 q Y $end
$upscope $end
$scope module _138_ $end
$var wire 1 q A $end
$var wire 1 0" B $end
$var wire 1 o Y $end
$upscope $end
$scope module _139_ $end
$var wire 1 | A $end
$var wire 1 m B $end
$var wire 1 n Y $end
$upscope $end
$scope module _140_ $end
$var wire 1 n A $end
$var wire 1 /" B $end
$var wire 1 k Y $end
$upscope $end
$scope module _141_ $end
$var wire 1 k A $end
$var wire 1 o B $end
$var wire 1 j Y $end
$upscope $end
$scope module _142_ $end
$var wire 1 j A $end
$var wire 1 r B $end
$var wire 1 h Y $end
$upscope $end
$scope module _143_ $end
$var wire 1 h A $end
$var wire 1 u B $end
$var wire 1 Q Y $end
$upscope $end
$scope module _144_ $end
$var wire 1 g A $end
$var wire 1 f Y $end
$upscope $end
$scope module _145_ $end
$var wire 1 w A $end
$var wire 1 f B $end
$var wire 1 e Y $end
$upscope $end
$scope module _146_ $end
$var wire 1 q A $end
$var wire 1 ." B $end
$var wire 1 c Y $end
$upscope $end
$scope module _147_ $end
$var wire 1 n A $end
$var wire 1 -" B $end
$var wire 1 b Y $end
$upscope $end
$scope module _148_ $end
$var wire 1 b A $end
$var wire 1 c B $end
$var wire 1 ` Y $end
$upscope $end
$scope module _149_ $end
$var wire 1 ` A $end
$var wire 1 e B $end
$var wire 1 _ Y $end
$upscope $end
$scope module _150_ $end
$var wire 1 _ A $end
$var wire 1 u B $end
$var wire 1 O Y $end
$upscope $end
$scope module _151_ $end
$var wire 1 d A $end
$var wire 1 ] Y $end
$upscope $end
$scope module _152_ $end
$var wire 1 w A $end
$var wire 1 ] B $end
$var wire 1 [ Y $end
$upscope $end
$scope module _153_ $end
$var wire 1 q A $end
$var wire 1 ," B $end
$var wire 1 Z Y $end
$upscope $end
$scope module _154_ $end
$var wire 1 n A $end
$var wire 1 +" B $end
$var wire 1 X Y $end
$upscope $end
$scope module _155_ $end
$var wire 1 X A $end
$var wire 1 Z B $end
$var wire 1 W Y $end
$upscope $end
$scope module _156_ $end
$var wire 1 W A $end
$var wire 1 [ B $end
$var wire 1 U Y $end
$upscope $end
$scope module _157_ $end
$var wire 1 U A $end
$var wire 1 u B $end
$var wire 1 M Y $end
$upscope $end
$scope module _158_ $end
$var wire 1 a A $end
$var wire 1 T Y $end
$upscope $end
$scope module _159_ $end
$var wire 1 w A $end
$var wire 1 T B $end
$var wire 1 S Y $end
$upscope $end
$scope module _160_ $end
$var wire 1 q A $end
$var wire 1 *" B $end
$var wire 1 P Y $end
$upscope $end
$scope module _161_ $end
$var wire 1 n A $end
$var wire 1 )" B $end
$var wire 1 N Y $end
$upscope $end
$scope module _162_ $end
$var wire 1 N A $end
$var wire 1 P B $end
$var wire 1 L Y $end
$upscope $end
$scope module _163_ $end
$var wire 1 L A $end
$var wire 1 S B $end
$var wire 1 J Y $end
$upscope $end
$scope module _164_ $end
$var wire 1 J A $end
$var wire 1 u B $end
$var wire 1 K Y $end
$upscope $end
$scope module _165_ $end
$var wire 1 ^ A $end
$var wire 1 G Y $end
$upscope $end
$scope module _166_ $end
$var wire 1 w A $end
$var wire 1 G B $end
$var wire 1 E Y $end
$upscope $end
$scope module _167_ $end
$var wire 1 q A $end
$var wire 1 (" B $end
$var wire 1 C Y $end
$upscope $end
$scope module _168_ $end
$var wire 1 n A $end
$var wire 1 '" B $end
$var wire 1 A Y $end
$upscope $end
$scope module _169_ $end
$var wire 1 A A $end
$var wire 1 C B $end
$var wire 1 @ Y $end
$upscope $end
$scope module _170_ $end
$var wire 1 @ A $end
$var wire 1 E B $end
$var wire 1 ? Y $end
$upscope $end
$scope module _171_ $end
$var wire 1 ? A $end
$var wire 1 u B $end
$var wire 1 I Y $end
$upscope $end
$scope module _172_ $end
$var wire 1 \ A $end
$var wire 1 > Y $end
$upscope $end
$scope module _173_ $end
$var wire 1 w A $end
$var wire 1 > B $end
$var wire 1 = Y $end
$upscope $end
$scope module _174_ $end
$var wire 1 q A $end
$var wire 1 &" B $end
$var wire 1 < Y $end
$upscope $end
$scope module _175_ $end
$var wire 1 n A $end
$var wire 1 %" B $end
$var wire 1 ; Y $end
$upscope $end
$scope module _176_ $end
$var wire 1 ; A $end
$var wire 1 < B $end
$var wire 1 9 Y $end
$upscope $end
$scope module _177_ $end
$var wire 1 9 A $end
$var wire 1 = B $end
$var wire 1 7 Y $end
$upscope $end
$scope module _178_ $end
$var wire 1 7 A $end
$var wire 1 u B $end
$var wire 1 H Y $end
$upscope $end
$scope module _179_ $end
$var wire 1 Y A $end
$var wire 1 6 Y $end
$upscope $end
$scope module _180_ $end
$var wire 1 w A $end
$var wire 1 6 B $end
$var wire 1 ;" Y $end
$upscope $end
$scope module _181_ $end
$var wire 1 q A $end
$var wire 1 $" B $end
$var wire 1 :" Y $end
$upscope $end
$scope module _182_ $end
$var wire 1 n A $end
$var wire 1 #" B $end
$var wire 1 9" Y $end
$upscope $end
$scope module _183_ $end
$var wire 1 9" A $end
$var wire 1 :" B $end
$var wire 1 8" Y $end
$upscope $end
$scope module _184_ $end
$var wire 1 8" A $end
$var wire 1 ;" B $end
$var wire 1 7" Y $end
$upscope $end
$scope module _185_ $end
$var wire 1 7" A $end
$var wire 1 u B $end
$var wire 1 F Y $end
$upscope $end
$scope module _186_ $end
$var wire 1 V A $end
$var wire 1 6" Y $end
$upscope $end
$scope module _187_ $end
$var wire 1 w A $end
$var wire 1 6" B $end
$var wire 1 5" Y $end
$upscope $end
$scope module _188_ $end
$var wire 1 q A $end
$var wire 1 "" B $end
$var wire 1 4" Y $end
$upscope $end
$scope module _189_ $end
$var wire 1 n A $end
$var wire 1 !" B $end
$var wire 1 3" Y $end
$upscope $end
$scope module _190_ $end
$var wire 1 3" A $end
$var wire 1 4" B $end
$var wire 1 2" Y $end
$upscope $end
$scope module _191_ $end
$var wire 1 2" A $end
$var wire 1 5" B $end
$var wire 1 1" Y $end
$upscope $end
$scope module _192_ $end
$var wire 1 1" A $end
$var wire 1 u B $end
$var wire 1 D Y $end
$upscope $end
$scope module _193_ $end
$var wire 1 n A $end
$var wire 1 2 B $end
$var wire 1 : Y $end
$upscope $end
$scope module _194_ $end
$var wire 1 w A $end
$var wire 1 8 Y $end
$upscope $end
$scope module _195_ $end
$var wire 1 @" D $end
$var wire 1 - C $end
$var reg 1 A" Q $end
$upscope $end
$scope module _196_ $end
$var wire 1 B" D $end
$var wire 1 - C $end
$var reg 1 C" Q $end
$upscope $end
$scope module _197_ $end
$var wire 1 D" D $end
$var wire 1 - C $end
$var reg 1 E" Q $end
$upscope $end
$scope module _198_ $end
$var wire 1 F" D $end
$var wire 1 - C $end
$var reg 1 G" Q $end
$upscope $end
$scope module _199_ $end
$var wire 1 H" D $end
$var wire 1 - C $end
$var reg 1 I" Q $end
$upscope $end
$scope module _200_ $end
$var wire 1 J" D $end
$var wire 1 - C $end
$var reg 1 K" Q $end
$upscope $end
$scope module _201_ $end
$var wire 1 L" D $end
$var wire 1 - C $end
$var reg 1 M" Q $end
$upscope $end
$scope module _202_ $end
$var wire 1 N" D $end
$var wire 1 - C $end
$var reg 1 O" Q $end
$upscope $end
$scope module _203_ $end
$var wire 1 P" D $end
$var wire 1 - C $end
$var reg 1 Q" Q $end
$upscope $end
$scope module _204_ $end
$var wire 1 R" D $end
$var wire 1 - C $end
$var reg 1 S" Q $end
$upscope $end
$upscope $end
$scope module p $end
$var reg 1 - CLK $end
$var reg 1 , ENB $end
$var reg 2 T" PCLK [1:0] $end
$var reg 32 U" in [31:0] $end
$upscope $end
$upscope $end
$enddefinitions $end
#0
$dumpvars
bx U"
bx T"
xS"
xR"
xQ"
xP"
xO"
0N"
xM"
0L"
xK"
0J"
xI"
0H"
xG"
0F"
xE"
0D"
xC"
0B"
xA"
0@"
bx ?"
b0 >"
bx ="
x<"
x;"
x:"
x9"
x8"
x7"
x6"
x5"
x4"
x3"
x2"
x1"
x0"
x/"
x."
x-"
x,"
x+"
x*"
x)"
x("
x'"
x&"
x%"
x$"
x#"
x""
x!"
x~
x}
x|
x{
xz
xy
xx
xw
xv
1u
xt
xs
xr
xq
xp
xo
xn
xm
xl
xk
xj
xi
xh
xg
xf
xe
xd
xc
xb
xa
x`
x_
x^
x]
x\
x[
xZ
xY
xX
xW
xV
xU
xT
xS
xR
0Q
xP
0O
xN
0M
xL
0K
xJ
0I
0H
xG
0F
xE
0D
xC
xB
xA
x@
x?
x>
x=
x<
x;
x:
x9
x8
x7
x6
bx 5
bx 4
bx 3
02
bx 1
bx 0
bx /
bx .
0-
0,
bx +
bx *
bx )
bx (
x'
z&
z%
z$
z#
z"
z!
$end
#10
0A"
0C"
0E"
0G"
0I"
0K"
0M"
b0 (
b0 4
0O"
b0 1
1-
#20
0-
x@"
xB"
xD"
xF"
xH"
xJ"
xL"
xN"
xQ
xO
xM
xK
xI
xH
xF
bx >"
xD
0P"
bx0 ="
0:
0u
12
1,
#30
0Q"
xO"
xM"
xK"
xI"
xG"
xE"
xC"
xA"
bx (
bx 4
bx 1
1-
#40
0-
#50
1-
#60
0-
#70
1-
#80
0-
#90
1-
#100
0H"
0L"
0I
0F
0J"
0N"
1@"
1B"
1D"
1F"
0H
0D
1Q
1O
1M
b1111 >"
1K
1?
17"
17
11"
0h
0_
0U
0J
0j
0W
0@
08"
0`
0L
09
02"
1r
1e
1[
1S
1R"
1k
1X
1A
19"
1<"
b10 ="
18
1o
1c
1Z
1P
1C
1<
1:"
14"
0w
05"
0;"
0=
0E
0n
13"
1;
1N
1b
1B
0q
1{
16"
16
1>
1G
0T
0]
0f
0t
1|
1y
0V
0Y
0\
0^
1a
1d
1g
1i
0l
0p
0s
0v
0x
0z
0}
0~
0!"
1""
1#"
1$"
0%"
1&"
1'"
1("
0)"
1*"
1+"
1,"
0-"
1."
1/"
10"
0R
0m
b11 0
0-
b1111000000001111111101010101 *
b1111000000001111111101010101 .
b1111000000001111111101010101 5
b1111000000001111111101010101 U"
b0 +
b0 /
b0 ?"
b0 T"
#110
b1x )
b1x 3
1S"
0O"
0M"
0K"
0I"
1G"
1E"
1C"
b1111 (
b1111 4
1A"
b10 0
b1111 1
1-
#120
0-
#130
bx )
bx 3
b1 0
b0xxxx (
b0xxxx 4
b0 1
1-
#140
0-
#150
b0 0
bx1111 (
bx1111 4
b11111111 1
1-
#160
0-
#170
b0x0xx1x1 (
b0x0xx1x1 4
b1010101 1
1-
#175
1H"
1J"
1L"
1N"
1I
1H
1F
b11111111 >"
1D
0?
07
07"
01"
1j
1`
1W
1L
1@
19
18"
12"
0r
0e
0[
0S
0R"
0<"
b0 ="
08
0o
0c
0Z
0P
0C
0<
0:"
04"
1w
1q
0{
0y
1m
b1 0
b1 +
b1 /
b1 ?"
b1 T"
#180
0N"
0L"
0F"
0D"
0B"
0@"
0D
0F
0K
0M
0O
b110000 >"
0Q
11"
17"
1J
1U
1_
1h
02"
08"
0L
0W
0`
0j
14"
1:"
1P
1Z
1c
1o
1T
1]
1f
1t
0a
0d
0g
0i
1!"
0""
0$"
1%"
0'"
1)"
0*"
0+"
0,"
1-"
0."
0/"
00"
b11000011101010 *
b11000011101010 .
b11000011101010 5
b11000011101010 U"
0-
#190
b0x )
b0x 3
0S"
1K"
1I"
0G"
0E"
0C"
0A"
b0 0
b110000 (
b110000 4
b110000 1
1-
#200
0-
#210
bx1xx0x0 (
bx1xx0x0 4
b11101010 1
1-
#220
0-
#230
1-
#240
0-
#250
1-
