src/convertidor832.v
module convertidor(PCLK,in,out,ENB,CLK,bits,part);
		input wire [1:0] PCLK;
		input wire CLK;
		input wire ENB;
		input wire [7:0] in;
		output reg [31:0] out;
		output reg [1:0] bits;
		output reg [31:0] part;
		always @(PCLK)
		begin
		case(PCLK[1:0])
			2'b00: bits=2'b11;
			2'b01: 
			begin
				bits=2'b01;
				part[31:16]=0;
			end
			2'b10:
			begin
				bits=2'b00;
				part[31:8]=0;
			end
			2'b11: bits=2'b11;
		endcase
		end
		always @(posedge CLK) begin
			if(ENB==1) begin
				if(bits==2'b11)begin
					part[31:24]<=in[7:0];
					bits<=2'b10;
					out<=0;
				end 
				else if(bits==2'b10)begin
					part[23:16]<=in[7:0];
					bits<=2'b01;
					out<=0;
				end 
				else if(bits==2'b01)begin
					part[15:8]<=in[7:0];
					bits<=2'b00;
					out<=0;
				end
				else //(bits==2'b00)
				begin
					out[31:8]<=part[31:8];
					out[7:0]<=in[7:0];
				end 
			end
			else 
			begin
				out=0;
			end	
		end
	endmodule

src/probador_conv832.v
module probador_conv(PCLK,ENB,in,CLK);

	output reg [1:0] PCLK;
	output reg CLK;
	output reg ENB;
  	output reg [7:0] in;
	
	initial begin
		CLK=0;
		ENB=0;
		
		#18 ENB=1;
		#80
		PCLK<=2'b00;//32bits
        	in<=32'b00001111;
		#20
        	in<=32'b11110000;
		#20
        	in<=32'b10101010;
		#20
        	in<=32'b01010000;
		#20
		PCLK<=2'b01;//16bits
        	in<=32'b01110000;
		#20
        	in<=32'b00010000;
		#20
		PCLK<=2'b10;//8bits
        	in<=32'b11010000;
		#20
        	in<=32'b11110000;
		#20
        	in<=32'b10101110;
	
		#150
	  	$finish;
	end
	always begin
        	#10 CLK <= ~CLK;
      	end
	
endmodule

src/probador_conv832_tb.v
`include "convertidor832.v"
`include "probador_conv832.v"

module probador_conv832_tb();

input wire [1:0] PCLK;
input wire [7:0] in_data;
input wire CLK, ENB;
output wire [31:0] OUT_DATA;
output wire [1:0] bit;
output wire [31:0] part;

probador_conv p(PCLK,ENB,in_data,CLK);
convertidor conv(PCLK, in_data, OUT_DATA, ENB, CLK, bit,part);


initial 
	begin
	$dumpfile("conv832.vcd");
	$dumpvars;
	end

endmodule

src/conv832.vcd
$date
	Wed Oct 18 00:13:26 2017
$end
$version
	Icarus Verilog
$end
$timescale
	1s
$end
$scope module probador_conv832_tb $end
$var wire 32 ! part [31:0] $end
$var wire 8 " in_data [7:0] $end
$var wire 2 # bit [1:0] $end
$var wire 2 $ PCLK [1:0] $end
$var wire 32 % OUT_DATA [31:0] $end
$var wire 1 & ENB $end
$var wire 1 ' CLK $end
$scope module conv $end
$var wire 8 ( in [7:0] $end
$var wire 2 ) PCLK [1:0] $end
$var wire 1 & ENB $end
$var wire 1 ' CLK $end
$var reg 2 * bits [1:0] $end
$var reg 32 + out [31:0] $end
$var reg 32 , part [31:0] $end
$upscope $end
$scope module p $end
$var reg 1 ' CLK $end
$var reg 1 & ENB $end
$var reg 2 - PCLK [1:0] $end
$var reg 8 . in [7:0] $end
$upscope $end
$upscope $end
$enddefinitions $end
#0
$dumpvars
bx .
bx -
bx ,
bx +
bx *
bx )
bx (
0'
0&
bx %
bx $
bx #
bx "
bx !
$end
#10
b0 %
b0 +
1'
#18
1&
#20
0'
#30
bx %
bx +
1'
#40
0'
#50
1'
#60
0'
#70
1'
#80
0'
#90
1'
#98
b11 #
b11 *
b1111 "
b1111 (
b1111 .
b0 $
b0 )
b0 -
#100
0'
#110
b0 %
b0 +
b10 #
b10 *
b1111xxxxxxxxxxxxxxxxxxxxxxxx !
b1111xxxxxxxxxxxxxxxxxxxxxxxx ,
1'
#118
b11110000 "
b11110000 (
b11110000 .
#120
0'
#130
b1 #
b1 *
b111111110000xxxxxxxxxxxxxxxx !
b111111110000xxxxxxxxxxxxxxxx ,
1'
#138
b10101010 "
b10101010 (
b10101010 .
#140
0'
#150
b0 #
b0 *
b11111111000010101010xxxxxxxx !
b11111111000010101010xxxxxxxx ,
1'
#158
b1010000 "
b1010000 (
b1010000 .
#160
0'
#170
b1111111100001010101001010000 %
b1111111100001010101001010000 +
1'
#178
b10101010xxxxxxxx !
b10101010xxxxxxxx ,
b1 #
b1 *
b1110000 "
b1110000 (
b1110000 .
b1 $
b1 )
b1 -
#180
0'
#190
b0 %
b0 +
b0 #
b0 *
b1110000xxxxxxxx !
b1110000xxxxxxxx ,
1'
#198
b10000 "
b10000 (
b10000 .
#200
0'
#210
b111000000010000 %
b111000000010000 +
1'
#218
b0xxxxxxxx !
b0xxxxxxxx ,
b11010000 "
b11010000 (
b11010000 .
b10 $
b10 )
b10 -
#220
0'
#230
b11010000 %
b11010000 +
1'
#238
b11110000 "
b11110000 (
b11110000 .
#240
0'
#250
b11110000 %
b11110000 +
1'
#258
b10101110 "
b10101110 (
b10101110 .
#260
0'
#270
b10101110 %
b10101110 +
1'
