src/convertidorsynt.v
/* Generated by Yosys 0.7 (git sha1 61f6811, gcc 6.2.0-10 -O2 -fdebug-prefix-map=/build/yosys-0DEyT5/yosys-0.7=. -fstack-protector-strong -fPIC -Os) */
`include "cmos_cells.v"

module convertidorsynt(PCLK, in, out_8, ENB, CLK, bits);
  wire [7:0] _000_;
  wire [1:0] _001_;
  wire _002_;
  wire _003_;
  wire _004_;
  wire _005_;
  wire _006_;
  wire _007_;
  wire _008_;
  wire _009_;
  wire _010_;
  wire _011_;
  wire _012_;
  wire _013_;
  wire _014_;
  wire _015_;
  wire _016_;
  wire _017_;
  wire _018_;
  wire _019_;
  wire _020_;
  wire _021_;
  wire _022_;
  wire _023_;
  wire _024_;
  wire _025_;
  wire _026_;
  wire _027_;
  wire _028_;
  wire _029_;
  wire _030_;
  wire _031_;
  wire _032_;
  wire _033_;
  wire _034_;
  wire _035_;
  wire _036_;
  wire _037_;
  wire _038_;
  wire _039_;
  wire _040_;
  wire _041_;
  wire _042_;
  wire _043_;
  wire _044_;
  wire _045_;
  wire _046_;
  wire _047_;
  wire _048_;
  wire _049_;
  wire _050_;
  wire _051_;
  wire _052_;
  wire _053_;
  wire _054_;
  wire _055_;
  wire _056_;
  wire _057_;
  wire _058_;
  wire _059_;
  wire _060_;
  wire _061_;
  wire _062_;
  wire _063_;
  wire _064_;
  wire _065_;
  wire _066_;
  wire _067_;
  wire _068_;
  wire _069_;
  wire _070_;
  wire _071_;
  wire _072_;
  wire _073_;
  wire _074_;
  wire [1:0] _075_;
  wire [1:0] _076_;
  wire _077_;
  wire _078_;
  wire _079_;
  wire [1:0] _080_;
  wire [5:0] _081_;
  wire [1:0] _082_;
  wire _083_;
  wire _084_;
  wire _085_;
  wire [7:0] _086_;
  wire _087_;
  input CLK;
  input ENB;
  input [1:0] PCLK;
  output [1:0] bits;
  input [31:0] in;
  output [7:0] out_8;
  NOT _088_ (
    .A(_002_),
    .Y(_014_)
  );
  NAND _089_ (
    .A(_025_),
    .B(_014_),
    .Y(_003_)
  );
  NOT _090_ (
    .A(_025_),
    .Y(_016_)
  );
  NAND _091_ (
    .A(_016_),
    .B(_002_),
    .Y(_018_)
  );
  NAND _092_ (
    .A(_018_),
    .B(_003_),
    .Y(_020_)
  );
  NOT _093_ (
    .A(_020_),
    .Y(_004_)
  );
  NOR _094_ (
    .A(_016_),
    .B(_002_),
    .Y(_022_)
  );
  NOR _095_ (
    .A(_022_),
    .B(_006_),
    .Y(_024_)
  );
  NOT _096_ (
    .A(_005_),
    .Y(_026_)
  );
  NAND _097_ (
    .A(_022_),
    .B(_026_),
    .Y(_028_)
  );
  NAND _098_ (
    .A(_028_),
    .B(_032_),
    .Y(_030_)
  );
  NOR _099_ (
    .A(_030_),
    .B(_024_),
    .Y(_034_)
  );
  NOR _100_ (
    .A(_022_),
    .B(_008_),
    .Y(_031_)
  );
  NOT _101_ (
    .A(_007_),
    .Y(_033_)
  );
  NAND _102_ (
    .A(_022_),
    .B(_033_),
    .Y(_035_)
  );
  NAND _103_ (
    .A(_035_),
    .B(_032_),
    .Y(_037_)
  );
  NOR _104_ (
    .A(_037_),
    .B(_031_),
    .Y(_036_)
  );
  NOR _105_ (
    .A(_022_),
    .B(_010_),
    .Y(_040_)
  );
  NOT _106_ (
    .A(_009_),
    .Y(_042_)
  );
  NAND _107_ (
    .A(_022_),
    .B(_042_),
    .Y(_044_)
  );
  NAND _108_ (
    .A(_044_),
    .B(_032_),
    .Y(_046_)
  );
  NOR _109_ (
    .A(_046_),
    .B(_040_),
    .Y(_038_)
  );
  NOR _110_ (
    .A(_022_),
    .B(_012_),
    .Y(_048_)
  );
  NOT _111_ (
    .A(_011_),
    .Y(_049_)
  );
  NAND _112_ (
    .A(_022_),
    .B(_049_),
    .Y(_050_)
  );
  NAND _113_ (
    .A(_050_),
    .B(_032_),
    .Y(_052_)
  );
  NOR _114_ (
    .A(_052_),
    .B(_048_),
    .Y(_039_)
  );
  NOR _115_ (
    .A(_022_),
    .B(_015_),
    .Y(_054_)
  );
  NOT _116_ (
    .A(_013_),
    .Y(_055_)
  );
  NAND _117_ (
    .A(_022_),
    .B(_055_),
    .Y(_056_)
  );
  NAND _118_ (
    .A(_056_),
    .B(_032_),
    .Y(_057_)
  );
  NOR _119_ (
    .A(_057_),
    .B(_054_),
    .Y(_041_)
  );
  NOR _120_ (
    .A(_022_),
    .B(_019_),
    .Y(_058_)
  );
  NOT _121_ (
    .A(_017_),
    .Y(_059_)
  );
  NAND _122_ (
    .A(_022_),
    .B(_059_),
    .Y(_060_)
  );
  NAND _123_ (
    .A(_060_),
    .B(_032_),
    .Y(_061_)
  );
  NOR _124_ (
    .A(_061_),
    .B(_058_),
    .Y(_043_)
  );
  NOR _125_ (
    .A(_022_),
    .B(_023_),
    .Y(_062_)
  );
  NOT _126_ (
    .A(_021_),
    .Y(_063_)
  );
  NAND _127_ (
    .A(_022_),
    .B(_063_),
    .Y(_064_)
  );
  NAND _128_ (
    .A(_064_),
    .B(_032_),
    .Y(_065_)
  );
  NOR _129_ (
    .A(_065_),
    .B(_062_),
    .Y(_045_)
  );
  NOR _130_ (
    .A(_022_),
    .B(_029_),
    .Y(_066_)
  );
  NOT _131_ (
    .A(_027_),
    .Y(_067_)
  );
  NAND _132_ (
    .A(_022_),
    .B(_067_),
    .Y(_068_)
  );
  NAND _133_ (
    .A(_068_),
    .B(_032_),
    .Y(_069_)
  );
  NOR _134_ (
    .A(_069_),
    .B(_066_),
    .Y(_047_)
  );
  NAND _135_ (
    .A(_032_),
    .B(_014_),
    .Y(_070_)
  );
  NAND _136_ (
    .A(_070_),
    .B(_020_),
    .Y(_053_)
  );
  NAND _137_ (
    .A(_025_),
    .B(_014_),
    .Y(_051_)
  );
  DFF _138_ (
    .C(CLK),
    .D(_000_[0]),
    .Q(out_8[0])
  );
  DFF _139_ (
    .C(CLK),
    .D(_000_[1]),
    .Q(out_8[1])
  );
  DFF _140_ (
    .C(CLK),
    .D(_000_[2]),
    .Q(out_8[2])
  );
  DFF _141_ (
    .C(CLK),
    .D(_000_[3]),
    .Q(out_8[3])
  );
  DFF _142_ (
    .C(CLK),
    .D(_000_[4]),
    .Q(out_8[4])
  );
  DFF _143_ (
    .C(CLK),
    .D(_000_[5]),
    .Q(out_8[5])
  );
  DFF _144_ (
    .C(CLK),
    .D(_000_[6]),
    .Q(out_8[6])
  );
  DFF _145_ (
    .C(CLK),
    .D(_000_[7]),
    .Q(out_8[7])
  );
  DFF _146_ (
    .C(CLK),
    .D(_001_[0]),
    .Q(bits[0])
  );
  DFF _147_ (
    .C(CLK),
    .D(_001_[1]),
    .Q(bits[1])
  );
  assign _002_ = PCLK[0];
  assign _025_ = PCLK[1];
  assign bits[0] = _003_;
  assign bits[1] = _004_;
  assign _005_ = in[24];
  assign _006_ = out_8[0];
  assign _007_ = in[25];
  assign _008_ = out_8[1];
  assign _009_ = in[26];
  assign _010_ = out_8[2];
  assign _011_ = in[27];
  assign _012_ = out_8[3];
  assign _013_ = in[28];
  assign _015_ = out_8[4];
  assign _017_ = in[29];
  assign _019_ = out_8[5];
  assign _021_ = in[30];
  assign _023_ = out_8[6];
  assign _027_ = in[31];
  assign _029_ = out_8[7];
  assign _032_ = ENB;
  assign _000_[0] = _034_;
  assign _000_[1] = _036_;
  assign _000_[2] = _038_;
  assign _000_[3] = _039_;
  assign _000_[4] = _041_;
  assign _000_[5] = _043_;
  assign _000_[6] = _045_;
  assign _000_[7] = _047_;
  assign _001_[0] = _051_;
  assign _001_[1] = _053_;
endmodule

src/convertidor.v
module convertidor(PCLK,in,out_8,ENB,CLK);
		input wire [1:0] PCLK;
		input wire CLK;
		input wire ENB;
		input wire [31:0] in;
		output reg [7:0] out_8;
		reg [1:0] bits;
		
		always @(*)
		begin
		case(PCLK[1:0])
			2'b00: bits=2'b11;
			2'b01: bits=2'b01;
			2'b10: bits=2'b00;
			2'b11: bits=2'b11;
		endcase
		end
		always @(posedge CLK) begin
			if(ENB==1) begin
				if(bits==2'b11)begin
					out_8[7:0]<=in[31:24];
					bits<=2'b10;
				end 
				else if(bits==2'b10)begin
					out_8[7:0]<=in[23:16];
					bits<=2'b01;
				end 
				else if(bits==2'b01)begin
					out_8[7:0]<=in[15:8];
					bits<=2'b00;
				end
				else //(bits==2'b00)
				begin
					bits <=2'b11;
					out_8[7:0]<=in[7:0];
				end 
			end
			else 
			begin
				bits <=2'b11;
				out_8=0;
			end	
		end
	endmodule

src/probador_conv.v
module probador_conv(CLK, PCLK, in, K, RESET_PS, RESET_PLL, ENB, RESET_SP, RESET_CONV832);

	output reg [1:0] PCLK;
	output reg CLK, K, RESET_PLL, RESET_SP, RESET_PS , ENB, RESET_CONV832;
  	output reg [31:0] in;
	
	initial begin
		$dumpfile ("Tx.vcd");
		$dumpvars;
		CLK<=0;
		ENB<=0;
		K<=0;
		RESET_PLL<=0;
		RESET_PS<=0;
		RESET_SP<=0;
		RESET_CONV832<=0;
		
		#10 
		RESET_PLL<=1;
		#10
		ENB<=1;
		
		#180
		PCLK<=2'b00;//32bits
        	in<=32'b00001111000000001111111101010101;
		#10
		RESET_PS<=1;
		#5
		RESET_SP<=1;
		#95
		RESET_CONV832<=1;
		#290
        	in<=32'b10101010000011110000000011111111;
		#400
        	in<=32'b00001111111100001111111100000000;
		#400
	
			in<=32'b00110000111010100011000011101010;
		#400
        	in<=32'b10101010111111110000000010101010;
	
		#800
	  	$finish;
	end
	always begin
        	#5 CLK <= ~CLK;
      	end
	
endmodule

src/probador_conv_tb.v
`include "convertidor.v"
`include "convertidorsynt.v"
`include "probador_conv.v"

module probador_conv_tb();

input wire [1:0] PCLK;
input wire [31:0] in_data;
input wire CLK, ENB;
output wire [7:0] OUT_DATA;
output wire [1:0] bit;

probador_conv p(PCLK,ENB,in_data,CLK);
convertidor conv(PCLK, in_data, OUT_DATA, ENB, CLK, bit);
convertidorsynt convsynt(PCLK,in_data, OUT_DATA, ENB, CLK, bit);


initial 
	begin
	$dumpfile("conv328.vcd");
	$dumpvars;
	end

endmodule

src/cmos_cellspotencia.v

module BUF(A, Y);
	input A;
	output Y;
	assign Y = A;
endmodule

module NOT(A, Y);
	input A;
	output Y;
	assign Y = ~A;
endmodule

module NAND(A, B, Y);
	input A, B;
	output Y;
	assign Y = ~(A & B);
endmodule

module NOR(A, B, Y);
	input A, B;
	output Y;
	assign Y = ~(A | B);
endmodule

module DFF(C, D, Q);
	parameter
		PwrC = 0;
	input C, D;
	output reg Q;
	always @(posedge C) begin
		Q <= D;
	end
	always @(posedge Q) begin
		tb_tx.m1.PwrCntr[PwrC] = tb_tx.m1.PwrCntr[PwrC] + 1;
	end
endmodule

module DFFSR(C, D, Q, S, R);
	input C, D, S, R;
	output reg Q;
	always @(posedge C, posedge S, posedge R)
		if (S)
			Q <= 1'b1;
		else if (R)
			Q <= 1'b0;
		else
			Q <= D;
endmodule

src/conv328.vcd
$date
	Wed Oct 18 00:13:26 2017
$end
$version
	Icarus Verilog
$end
$timescale
	1s
$end
$scope module BUF $end
$var wire 1 ! A $end
$var wire 1 " Y $end
$upscope $end
$scope module DFFSR $end
$var wire 1 # C $end
$var wire 1 $ D $end
$var wire 1 % R $end
$var wire 1 & S $end
$var reg 1 ' Q $end
$upscope $end
$scope module probador_conv_tb $end
$var wire 8 ( OUT_DATA [7:0] $end
$var wire 2 ) bit [1:0] $end
$var wire 32 * in_data [31:0] $end
$var wire 2 + PCLK [1:0] $end
$var wire 1 , ENB $end
$var wire 1 - CLK $end
$scope module conv $end
$var wire 32 . in [31:0] $end
$var wire 2 / PCLK [1:0] $end
$var wire 1 , ENB $end
$var wire 1 - CLK $end
$var reg 2 0 bits [1:0] $end
$var reg 8 1 out_8 [7:0] $end
$upscope $end
$scope module convsynt $end
$var wire 1 2 _032_ $end
$var wire 2 3 bits [1:0] $end
$var wire 8 4 out_8 [7:0] $end
$var wire 32 5 in [31:0] $end
$var wire 1 6 _070_ $end
$var wire 1 7 _069_ $end
$var wire 1 8 _068_ $end
$var wire 1 9 _067_ $end
$var wire 1 : _066_ $end
$var wire 1 ; _065_ $end
$var wire 1 < _064_ $end
$var wire 1 = _063_ $end
$var wire 1 > _062_ $end
$var wire 1 ? _061_ $end
$var wire 1 @ _060_ $end
$var wire 1 A _059_ $end
$var wire 1 B _058_ $end
$var wire 1 C _057_ $end
$var wire 1 D _056_ $end
$var wire 1 E _055_ $end
$var wire 1 F _054_ $end
$var wire 1 G _053_ $end
$var wire 1 H _052_ $end
$var wire 1 I _051_ $end
$var wire 1 J _050_ $end
$var wire 1 K _049_ $end
$var wire 1 L _048_ $end
$var wire 1 M _047_ $end
$var wire 1 N _046_ $end
$var wire 1 O _045_ $end
$var wire 1 P _044_ $end
$var wire 1 Q _043_ $end
$var wire 1 R _042_ $end
$var wire 1 S _041_ $end
$var wire 1 T _040_ $end
$var wire 1 U _039_ $end
$var wire 1 V _038_ $end
$var wire 1 W _037_ $end
$var wire 1 X _036_ $end
$var wire 1 Y _035_ $end
$var wire 1 Z _034_ $end
$var wire 1 [ _033_ $end
$var wire 1 \ _031_ $end
$var wire 1 ] _030_ $end
$var wire 1 ^ _029_ $end
$var wire 1 _ _028_ $end
$var wire 1 ` _027_ $end
$var wire 1 a _026_ $end
$var wire 1 b _025_ $end
$var wire 1 c _024_ $end
$var wire 1 d _023_ $end
$var wire 1 e _022_ $end
$var wire 1 f _021_ $end
$var wire 1 g _020_ $end
$var wire 1 h _019_ $end
$var wire 1 i _018_ $end
$var wire 1 j _017_ $end
$var wire 1 k _016_ $end
$var wire 1 l _015_ $end
$var wire 1 m _014_ $end
$var wire 1 n _013_ $end
$var wire 1 o _012_ $end
$var wire 1 p _011_ $end
$var wire 1 q _010_ $end
$var wire 1 r _009_ $end
$var wire 1 s _008_ $end
$var wire 1 t _007_ $end
$var wire 1 u _006_ $end
$var wire 1 v _005_ $end
$var wire 1 w _004_ $end
$var wire 1 x _003_ $end
$var wire 1 y _002_ $end
$var wire 2 z _001_ [1:0] $end
$var wire 8 { _000_ [7:0] $end
$var wire 2 | PCLK [1:0] $end
$var wire 1 , ENB $end
$var wire 1 - CLK $end
$scope module _088_ $end
$var wire 1 y A $end
$var wire 1 m Y $end
$upscope $end
$scope module _089_ $end
$var wire 1 b A $end
$var wire 1 m B $end
$var wire 1 x Y $end
$upscope $end
$scope module _090_ $end
$var wire 1 b A $end
$var wire 1 k Y $end
$upscope $end
$scope module _091_ $end
$var wire 1 k A $end
$var wire 1 y B $end
$var wire 1 i Y $end
$upscope $end
$scope module _092_ $end
$var wire 1 i A $end
$var wire 1 x B $end
$var wire 1 g Y $end
$upscope $end
$scope module _093_ $end
$var wire 1 g A $end
$var wire 1 w Y $end
$upscope $end
$scope module _094_ $end
$var wire 1 k A $end
$var wire 1 y B $end
$var wire 1 e Y $end
$upscope $end
$scope module _095_ $end
$var wire 1 e A $end
$var wire 1 u B $end
$var wire 1 c Y $end
$upscope $end
$scope module _096_ $end
$var wire 1 v A $end
$var wire 1 a Y $end
$upscope $end
$scope module _097_ $end
$var wire 1 e A $end
$var wire 1 a B $end
$var wire 1 _ Y $end
$upscope $end
$scope module _098_ $end
$var wire 1 _ A $end
$var wire 1 2 B $end
$var wire 1 ] Y $end
$upscope $end
$scope module _099_ $end
$var wire 1 ] A $end
$var wire 1 c B $end
$var wire 1 Z Y $end
$upscope $end
$scope module _100_ $end
$var wire 1 e A $end
$var wire 1 s B $end
$var wire 1 \ Y $end
$upscope $end
$scope module _101_ $end
$var wire 1 t A $end
$var wire 1 [ Y $end
$upscope $end
$scope module _102_ $end
$var wire 1 e A $end
$var wire 1 [ B $end
$var wire 1 Y Y $end
$upscope $end
$scope module _103_ $end
$var wire 1 Y A $end
$var wire 1 2 B $end
$var wire 1 W Y $end
$upscope $end
$scope module _104_ $end
$var wire 1 W A $end
$var wire 1 \ B $end
$var wire 1 X Y $end
$upscope $end
$scope module _105_ $end
$var wire 1 e A $end
$var wire 1 q B $end
$var wire 1 T Y $end
$upscope $end
$scope module _106_ $end
$var wire 1 r A $end
$var wire 1 R Y $end
$upscope $end
$scope module _107_ $end
$var wire 1 e A $end
$var wire 1 R B $end
$var wire 1 P Y $end
$upscope $end
$scope module _108_ $end
$var wire 1 P A $end
$var wire 1 2 B $end
$var wire 1 N Y $end
$upscope $end
$scope module _109_ $end
$var wire 1 N A $end
$var wire 1 T B $end
$var wire 1 V Y $end
$upscope $end
$scope module _110_ $end
$var wire 1 e A $end
$var wire 1 o B $end
$var wire 1 L Y $end
$upscope $end
$scope module _111_ $end
$var wire 1 p A $end
$var wire 1 K Y $end
$upscope $end
$scope module _112_ $end
$var wire 1 e A $end
$var wire 1 K B $end
$var wire 1 J Y $end
$upscope $end
$scope module _113_ $end
$var wire 1 J A $end
$var wire 1 2 B $end
$var wire 1 H Y $end
$upscope $end
$scope module _114_ $end
$var wire 1 H A $end
$var wire 1 L B $end
$var wire 1 U Y $end
$upscope $end
$scope module _115_ $end
$var wire 1 e A $end
$var wire 1 l B $end
$var wire 1 F Y $end
$upscope $end
$scope module _116_ $end
$var wire 1 n A $end
$var wire 1 E Y $end
$upscope $end
$scope module _117_ $end
$var wire 1 e A $end
$var wire 1 E B $end
$var wire 1 D Y $end
$upscope $end
$scope module _118_ $end
$var wire 1 D A $end
$var wire 1 2 B $end
$var wire 1 C Y $end
$upscope $end
$scope module _119_ $end
$var wire 1 C A $end
$var wire 1 F B $end
$var wire 1 S Y $end
$upscope $end
$scope module _120_ $end
$var wire 1 e A $end
$var wire 1 h B $end
$var wire 1 B Y $end
$upscope $end
$scope module _121_ $end
$var wire 1 j A $end
$var wire 1 A Y $end
$upscope $end
$scope module _122_ $end
$var wire 1 e A $end
$var wire 1 A B $end
$var wire 1 @ Y $end
$upscope $end
$scope module _123_ $end
$var wire 1 @ A $end
$var wire 1 2 B $end
$var wire 1 ? Y $end
$upscope $end
$scope module _124_ $end
$var wire 1 ? A $end
$var wire 1 B B $end
$var wire 1 Q Y $end
$upscope $end
$scope module _125_ $end
$var wire 1 e A $end
$var wire 1 d B $end
$var wire 1 > Y $end
$upscope $end
$scope module _126_ $end
$var wire 1 f A $end
$var wire 1 = Y $end
$upscope $end
$scope module _127_ $end
$var wire 1 e A $end
$var wire 1 = B $end
$var wire 1 < Y $end
$upscope $end
$scope module _128_ $end
$var wire 1 < A $end
$var wire 1 2 B $end
$var wire 1 ; Y $end
$upscope $end
$scope module _129_ $end
$var wire 1 ; A $end
$var wire 1 > B $end
$var wire 1 O Y $end
$upscope $end
$scope module _130_ $end
$var wire 1 e A $end
$var wire 1 ^ B $end
$var wire 1 : Y $end
$upscope $end
$scope module _131_ $end
$var wire 1 ` A $end
$var wire 1 9 Y $end
$upscope $end
$scope module _132_ $end
$var wire 1 e A $end
$var wire 1 9 B $end
$var wire 1 8 Y $end
$upscope $end
$scope module _133_ $end
$var wire 1 8 A $end
$var wire 1 2 B $end
$var wire 1 7 Y $end
$upscope $end
$scope module _134_ $end
$var wire 1 7 A $end
$var wire 1 : B $end
$var wire 1 M Y $end
$upscope $end
$scope module _135_ $end
$var wire 1 2 A $end
$var wire 1 m B $end
$var wire 1 6 Y $end
$upscope $end
$scope module _136_ $end
$var wire 1 6 A $end
$var wire 1 g B $end
$var wire 1 G Y $end
$upscope $end
$scope module _137_ $end
$var wire 1 b A $end
$var wire 1 m B $end
$var wire 1 I Y $end
$upscope $end
$scope module _138_ $end
$var wire 1 } D $end
$var wire 1 - C $end
$var reg 1 ~ Q $end
$upscope $end
$scope module _139_ $end
$var wire 1 !" D $end
$var wire 1 - C $end
$var reg 1 "" Q $end
$upscope $end
$scope module _140_ $end
$var wire 1 #" D $end
$var wire 1 - C $end
$var reg 1 $" Q $end
$upscope $end
$scope module _141_ $end
$var wire 1 %" D $end
$var wire 1 - C $end
$var reg 1 &" Q $end
$upscope $end
$scope module _142_ $end
$var wire 1 '" D $end
$var wire 1 - C $end
$var reg 1 (" Q $end
$upscope $end
$scope module _143_ $end
$var wire 1 )" D $end
$var wire 1 - C $end
$var reg 1 *" Q $end
$upscope $end
$scope module _144_ $end
$var wire 1 +" D $end
$var wire 1 - C $end
$var reg 1 ," Q $end
$upscope $end
$scope module _145_ $end
$var wire 1 -" D $end
$var wire 1 - C $end
$var reg 1 ." Q $end
$upscope $end
$scope module _146_ $end
$var wire 1 /" D $end
$var wire 1 - C $end
$var reg 1 0" Q $end
$upscope $end
$scope module _147_ $end
$var wire 1 1" D $end
$var wire 1 - C $end
$var reg 1 2" Q $end
$upscope $end
$upscope $end
$scope module p $end
$var reg 1 - CLK $end
$var reg 1 , ENB $end
$var reg 2 3" PCLK [1:0] $end
$var reg 32 4" in [31:0] $end
$upscope $end
$upscope $end
$enddefinitions $end
#0
$dumpvars
bx 4"
bx 3"
x2"
x1"
x0"
x/"
x."
0-"
x,"
0+"
x*"
0)"
x("
0'"
x&"
0%"
x$"
0#"
x""
0!"
x~
0}
bx |
b0 {
bx z
xy
xx
xw
xv
xu
xt
xs
xr
xq
xp
xo
xn
xm
xl
xk
xj
xi
xh
xg
xf
xe
xd
xc
xb
xa
x`
x_
x^
1]
x\
x[
0Z
xY
0X
1W
0V
0U
xT
0S
xR
0Q
xP
0O
1N
0M
xL
xK
xJ
xI
1H
xG
xF
xE
xD
1C
xB
xA
x@
1?
x>
x=
x<
1;
x:
x9
x8
17
16
bx 5
bx 4
bx 3
02
bx 1
bx 0
bx /
bx .
0-
0,
bx +
bx *
bx )
bx (
x'
z&
z%
z$
z#
z"
z!
$end
#10
0u
0s
0q
0o
0l
0h
0d
0^
0~
0""
0$"
0&"
0("
0*"
0,"
b0 (
b0 4
0."
b0 1
1-
#20
0-
x}
x!"
x#"
x%"
x'"
x)"
x+"
x-"
xZ
xX
xV
xU
xS
xQ
xO
bx {
xM
x]
xW
xN
xH
xC
x?
x;
x7
x6
12
1,
#30
xu
xs
xq
xo
xl
xh
xd
x^
x."
x,"
x*"
x("
x&"
x$"
x""
x~
bx (
bx 4
bx 1
1-
#40
0-
#50
1-
#60
0-
#70
1-
#80
0-
#90
1-
#100
0C
0?
0;
07
11"
0H
0N
0W
0]
1D
1@
1<
18
1G
1w
0g
1J
1P
1Y
1_
0e
1/"
06
1x
b11 z
1I
1i
19
1=
1A
1E
0K
0R
0[
0a
1k
1m
0`
0f
0j
0n
1p
1r
1t
1v
0b
0y
b11 0
0-
b1111000000001111111101010101 *
b1111000000001111111101010101 .
b1111000000001111111101010101 5
b1111000000001111111101010101 4"
b0 +
b0 /
b0 |
b0 3"
#110
b1x )
b1x 3
12"
10"
b10 0
b1111 1
1-
#120
0-
#130
bx1 )
bx1 3
b1 0
b0 1
1-
#140
0-
#150
bx )
bx 3
b0 0
b11111111 1
1-
#160
0-
#170
b1010101 1
1-
#175
01"
b1 z
0G
0w
1g
16
0i
0m
1y
bx1 )
bx1 3
b1 0
b1 +
b1 /
b1 |
b1 3"
#180
1K
1R
1[
1a
0p
0r
0t
0v
b11000011101010 *
b11000011101010 .
b11000011101010 5
b11000011101010 4"
0-
#190
02"
b0x )
b0x 3
b0 0
b110000 1
1-
#200
0-
#210
b11101010 1
1-
#220
0-
#230
1-
#240
0-
#250
1-
#260
0}
0!"
0#"
0%"
0'"
0)"
0+"
0-"
0Z
1]
0X
1W
0V
1N
0U
1H
0S
1C
0Q
1?
0O
1;
b0 {
0M
17
11"
0c
0_
0\
0Y
0T
0P
0L
0J
0F
0D
0B
0@
0>
0<
0:
08
1G
1e
0/"
06
0x
b10 z
0I
1i
0k
1m
1b
0y
0-
b10101110 *
b10101110 .
b10101110 5
b10101110 4"
b10 +
b10 /
b10 |
b10 3"
#270
0d
0l
0u
12"
bx0 )
bx0 3
00"
0."
0,"
0*"
0("
0&"
0$"
0""
bx0x0xxx0 (
bx0x0xxx0 4
0~
b10101110 1
1-
